Slash/__init__.py
Slash/types_.py
Slash/Core/__init__.py
Slash/Core/__main__.py
Slash/Core/core.py
Slash/Core/db_manager.py
Slash/Core/exceptions_.py
Slash/Core/migrate.py
Slash/Core/migration_templates.py
Slash/Core/operations_.py
Slash92-1.5.2.1.dist-info/LICENSE
Slash92-1.5.2.1.dist-info/METADATA
Slash92-1.5.2.1.dist-info/WHEEL
Slash92-1.5.2.1.dist-info/top_level.txt
Slash92-1.5.2.1.dist-info/RECORD
