Metadata-Version: 2.1
Name: Slash92
Version: 1.5.2.1
Summary: ORM
Home-page: https://github.com/m-o-d-e-r/Slash
Author: Telegram: @M_O_D_E_R
License: GPL-3.0
Platform: windows
Platform: linux
Requires-Python: >=3.8
License-File: LICENSE
Requires-Dist: psycopg2
